Metadata-Version: 2.1
Name: labxblock-xblock
Version: 0.4.14
Summary: labxblock XBlock
Home-page: UNKNOWN
License: UNKNOWN
Platform: UNKNOWN
